[
  {
    "line": 2,
    "elements": [
      {
        "line": 4,
        "name": "",
        "description": "",
        "type": "background",
        "keyword": "Background",
        "steps": [
          {
            "result": {
              "status": "skipped"
            },
            "line": 5,
            "name": "login with valid credentials",
            "match": {
              "location": "com.hrms.stepDefinitions.LoginStepDefinitions.login_with_valid_credentials()"
            },
            "keyword": "When "
          },
          {
            "result": {
              "duration": 1000000,
              "status": "skipped"
            },
            "line": 6,
            "name": "navigate to add employee page",
            "match": {
              "location": "com.hrms.stepDefinitions.AddEmpInstructorsStepDefninitions.navigate_to_add_employee_page()"
            },
            "keyword": "Then "
          }
        ]
      },
      {
        "start_timestamp": "2020-09-16T00:31:43.108Z",
        "before": [
          {
            "result": {
              "duration": 1000000,
              "status": "skipped"
            },
            "match": {
              "location": "com.hrms.stepDefinitions.Hooks.startTest()"
            }
          }
        ],
        "line": 22,
        "name": "Add employee without login details but with middle name",
        "description": "",
        "id": "add-employee;add-employee-without-login-details-but-with-middle-name",
        "after": [
          {
            "result": {
              "status": "skipped"
            },
            "match": {
              "location": "com.hrms.stepDefinitions.Hooks.endTest(io.cucumber.java.Scenario)"
            }
          }
        ],
        "type": "scenario",
        "keyword": "Scenario",
        "steps": [
          {
            "result": {
              "duration": 1000000,
              "status": "skipped"
            },
            "line": 23,
            "name": "enter first name as \"Ahmet\" middle name as \"Can\" and last name as \"Bicer\"",
            "match": {
              "arguments": [
                {
                  "val": "\"Ahmet\"",
                  "offset": 20
                },
                {
                  "val": "\"Can\"",
                  "offset": 43
                },
                {
                  "val": "\"Bicer\"",
                  "offset": 66
                }
              ],
              "location": "com.hrms.stepDefinitions.AddEmpInstructorsStepDefninitions.enter_first_name_as_middle_name_as_and_last_name_as(java.lang.String,java.lang.String,java.lang.String)"
            },
            "keyword": "When "
          },
          {
            "result": {
              "status": "skipped"
            },
            "line": 24,
            "name": "click on save Button",
            "match": {
              "location": "com.hrms.stepDefinitions.AddEmpInstructorsStepDefninitions.click_on_save_Button()"
            },
            "keyword": "Then "
          },
          {
            "result": {
              "duration": 1000000,
              "status": "skipped"
            },
            "line": 25,
            "name": "verify that \"Ahmet Can Bicer\" is added successfully",
            "match": {
              "arguments": [
                {
                  "val": "\"Ahmet Can Bicer\"",
                  "offset": 12
                }
              ],
              "location": "com.hrms.stepDefinitions.AddEmpInstructorsStepDefninitions.verify_that_is_added_successfully(java.lang.String)"
            },
            "keyword": "And "
          }
        ],
        "tags": [
          {
            "name": "@addEmployee"
          },
          {
            "name": "@parameter"
          }
        ]
      }
    ],
    "name": "Add Employee",
    "description": "",
    "id": "add-employee",
    "keyword": "Feature",
    "uri": "file:src/test/resources/features/AddEmployeeInstructorsWay.feature",
    "tags": [
      {
        "name": "@addEmployee",
        "type": "Tag",
        "location": {
          "line": 1,
          "column": 1
        }
      }
    ]
  }
]